Metadata-Version: 2.1
Name: localdeps
Version: 0.0.2
Summary: Install conda package dependencies into a conda environment
Home-page: https://github.com/cshaley/localdeps
Author: Charlie Haley
License: MIT License
Project-URL: Homepage, https://github.com/cshaley/localdeps
Project-URL: Bug Tracker, https://github.com/cshaley/localdeps/issues
Keywords: package dependency local development
Classifier: Programming Language :: Python :: 3
Classifier: License :: OSI Approved :: MIT License
Classifier: Operating System :: OS Independent
Requires-Python: >=3.4
License-File: LICENSE
